weight_converter/__init__.py
weight_converter/convert.py
weight_converter/interfaces.py
weight_converter/utils.py
weight_converter-0.0.3.dist-info/LICENSE.txt
weight_converter-0.0.3.dist-info/METADATA
weight_converter-0.0.3.dist-info/WHEEL
weight_converter-0.0.3.dist-info/top_level.txt
weight_converter-0.0.3.dist-info/RECORD
