Metadata-Version: 2.1
Name: weight-converter
Version: 0.0.3
Summary: Module for converting weight units. 
Home-page: https://github.com/adamriaz/weight-converter
Author: Adam Riaz
Author-email: riaz_adam@hotmail.com
License: MIT
Platform: UNKNOWN
Classifier: Programming Language :: Python :: 3
Classifier: Programming Language :: Python :: 3.9
Classifier: License :: OSI Approved :: MIT License
License-File: LICENSE.txt
